pixelle/.dockerignore
pixelle/.gitignore
pixelle/__init__.py
pixelle/cli.py
pixelle/logger.py
pixelle/main.py
pixelle/mcp_core.py
pixelle/settings.py
pixelle/.chainlit/config.toml
pixelle/.chainlit/translations/bn.json
pixelle/.chainlit/translations/el-GR.json
pixelle/.chainlit/translations/en-US.json
pixelle/.chainlit/translations/fr-FR.json
pixelle/.chainlit/translations/gu.json
pixelle/.chainlit/translations/he-IL.json
pixelle/.chainlit/translations/hi.json
pixelle/.chainlit/translations/ja.json
pixelle/.chainlit/translations/kn.json
pixelle/.chainlit/translations/ml.json
pixelle/.chainlit/translations/mr.json
pixelle/.chainlit/translations/nl.json
pixelle/.chainlit/translations/ta.json
pixelle/.chainlit/translations/te.json
pixelle/.chainlit/translations/zh-CN.json
pixelle/api/__init__.py
pixelle/api/files_api.py
pixelle/cli/__init__.py
pixelle/cli/__main__.py
pixelle/cli/main.py
pixelle/cli/commands/__init__.py
pixelle/cli/commands/dev.py
pixelle/cli/commands/edit.py
pixelle/cli/commands/init.py
pixelle/cli/commands/interactive.py
pixelle/cli/commands/logs.py
pixelle/cli/commands/reconfig.py
pixelle/cli/commands/start.py
pixelle/cli/commands/status.py
pixelle/cli/commands/stop.py
pixelle/cli/commands/workflow.py
pixelle/cli/interactive/__init__.py
pixelle/cli/interactive/menu.py
pixelle/cli/interactive/welcome.py
pixelle/cli/interactive/wizard.py
pixelle/cli/setup/__init__.py
pixelle/cli/setup/comfyui.py
pixelle/cli/setup/config_saver.py
pixelle/cli/setup/execution_engines.py
pixelle/cli/setup/runninghub.py
pixelle/cli/setup/service.py
pixelle/cli/setup/providers/__init__.py
pixelle/cli/setup/providers/claude.py
pixelle/cli/setup/providers/deepseek.py
pixelle/cli/setup/providers/gemini.py
pixelle/cli/setup/providers/manager.py
pixelle/cli/setup/providers/ollama.py
pixelle/cli/setup/providers/openai.py
pixelle/cli/setup/providers/qwen.py
pixelle/cli/utils/__init__.py
pixelle/cli/utils/command_utils.py
pixelle/cli/utils/display.py
pixelle-0.1.16.dist-info/METADATA
pixelle-0.1.16.dist-info/WHEEL
pixelle-0.1.16.dist-info/entry_points.txt
pixelle-0.1.16.dist-info/licenses/LICENSE
pixelle-0.1.16.dist-info/licenses/NOTICE
pixelle-0.1.16.dist-info/RECORD
